odoo10_addon_account_invoice_date_required-10.0.1.1.0.99.dev3-py3.8-nspkg.pth
odoo/addons/account_invoice_date_required/README.rst
odoo/addons/account_invoice_date_required/__init__.py
odoo/addons/account_invoice_date_required/__manifest__.py
odoo/addons/account_invoice_date_required/i18n/account_invoice_date_required.pot
odoo/addons/account_invoice_date_required/models/__init__.py
odoo/addons/account_invoice_date_required/models/account_config_settings.py
odoo/addons/account_invoice_date_required/models/account_invoice.py
odoo/addons/account_invoice_date_required/models/res_company.py
odoo/addons/account_invoice_date_required/readme/CONFIGURE.rst
odoo/addons/account_invoice_date_required/readme/CONTRIBUTORS.rst
odoo/addons/account_invoice_date_required/readme/DESCRIPTION.rst
odoo/addons/account_invoice_date_required/readme/USAGE.rst
odoo/addons/account_invoice_date_required/static/description/icon.png
odoo/addons/account_invoice_date_required/static/description/index.html
odoo/addons/account_invoice_date_required/tests/__init__.py
odoo/addons/account_invoice_date_required/tests/test_account_invoice.py
odoo/addons/account_invoice_date_required/views/account_config_settings.xml
odoo10_addon_account_invoice_date_required-10.0.1.1.0.99.dev3.dist-info/METADATA
odoo10_addon_account_invoice_date_required-10.0.1.1.0.99.dev3.dist-info/WHEEL
odoo10_addon_account_invoice_date_required-10.0.1.1.0.99.dev3.dist-info/namespace_packages.txt
odoo10_addon_account_invoice_date_required-10.0.1.1.0.99.dev3.dist-info/top_level.txt
odoo10_addon_account_invoice_date_required-10.0.1.1.0.99.dev3.dist-info/RECORD
